tln/__init__.py
tln/linears.py
tln/tln.py
tln/tsmixer.py
temporal_linear_network-0.1.2.dist-info/METADATA
temporal_linear_network-0.1.2.dist-info/WHEEL
temporal_linear_network-0.1.2.dist-info/RECORD
